iuselinux/__init__.py
iuselinux/api.py
iuselinux/config.py
iuselinux/contacts.py
iuselinux/db.py
iuselinux/messages.py
iuselinux/py.typed
iuselinux/sender.py
iuselinux/service.py
iuselinux/tray.py
iuselinux/updater.py
iuselinux/static/AppIcon.icns
iuselinux/static/android-chrome-192x192.png
iuselinux/static/android-chrome-512x512.png
iuselinux/static/app.js
iuselinux/static/apple-touch-icon.png
iuselinux/static/ding.mp3
iuselinux/static/error-no-access.html
iuselinux/static/favicon-16x16.png
iuselinux/static/favicon-32x32.png
iuselinux/static/favicon.ico
iuselinux/static/iconTemplate.png
iuselinux/static/iconTemplate@2x.png
iuselinux/static/index.html
iuselinux/static/styles.css
iuselinux/static/template.png
iuselinux-0.1.9.dist-info/METADATA
iuselinux-0.1.9.dist-info/WHEEL
iuselinux-0.1.9.dist-info/entry_points.txt
iuselinux-0.1.9.dist-info/licenses/LICENSE
iuselinux-0.1.9.dist-info/RECORD
