Metadata-Version: 2.4
Name: iuselinux
Version: 0.1.9
Summary: Remote iMessage gateway for macOS
Project-URL: Homepage, https://iuselinux.com
Project-URL: Repository, https://github.com/jbn/iuselinux
Project-URL: Issues, https://github.com/jbn/iuselinux/issues
Author-email: generativist <jbn@abreka.com>
License: MIT
License-File: LICENSE
Keywords: apple,gateway,imessage,macos,messages,sms
Classifier: Development Status :: 4 - Beta
Classifier: Environment :: Web Environment
Classifier: Framework :: FastAPI
Classifier: Intended Audience :: Developers
Classifier: Intended Audience :: End Users/Desktop
Classifier: License :: OSI Approved :: MIT License
Classifier: Operating System :: MacOS :: MacOS X
Classifier: Programming Language :: Python :: 3
Classifier: Programming Language :: Python :: 3.11
Classifier: Programming Language :: Python :: 3.12
Classifier: Programming Language :: Python :: 3.13
Classifier: Topic :: Communications :: Chat
Classifier: Topic :: Internet :: WWW/HTTP :: HTTP Servers
Classifier: Typing :: Typed
Requires-Python: >=3.11
Requires-Dist: click>=8.0.0
Requires-Dist: fastapi>=0.115.0
Requires-Dist: packaging>=21.0
Requires-Dist: pillow-heif>=1.1.1
Requires-Dist: pillow>=12.0.0
Requires-Dist: pydantic>=2.0.0
Requires-Dist: python-multipart>=0.0.20
Requires-Dist: rumps>=0.4.0; sys_platform == 'darwin'
Requires-Dist: uvicorn>=0.32.0
Requires-Dist: websockets>=15.0.1
Provides-Extra: dev
Requires-Dist: httpx>=0.28.0; extra == 'dev'
Requires-Dist: mypy>=1.14.0; extra == 'dev'
Requires-Dist: pytest>=9.0.1; extra == 'dev'
